README.rst
setup.py
browser_vulnerabilities/__init__.py
browser_vulnerabilities/data.py
browser_vulnerabilities.egg-info/PKG-INFO
browser_vulnerabilities.egg-info/SOURCES.txt
browser_vulnerabilities.egg-info/dependency_links.txt
browser_vulnerabilities.egg-info/requires.txt
browser_vulnerabilities.egg-info/top_level.txt