Metadata-Version: 1.1
Name: browser-vulnerabilities
Version: 0.1.0
Summary: Library for detecting vulnerable browsers
Home-page: https://github.com/ojarva/browser-vulnerabilities
Author: Olli Jarva
Author-email: olli@jarva.fi
License: MIT
Download-URL: https://github.com/ojarva/browser-vulnerabilities
Keywords: browser user-agent vulnerability
Platform: UNKNOWN
Classifier: Development Status :: 3 - Alpha
Classifier: Topic :: Software Development :: Libraries
Classifier: License :: OSI Approved :: MIT License
